{"date": "02/01/2016", "responses": "200", "description": "No Points", "comments": "RAMA", "time": "02:09 PM"}
{"date": "02/01/2016", "responses": "200", "description": "Duration of a microstate", "comments": "RAMA", "time": "02:10 PM"}
{"date": "02/01/2016", "responses": "206", "description": "BEQ", "comments": "RAMA", "time": "02:14 PM"}
{"date": "02/01/2016", "responses": "216", "description": "Z-bit modifier", "comments": "RAMA", "time": "02:41 PM"}
{"date": "02/01/2016", "responses": "218", "description": "OP input to modifier", "comments": "RAMA", "time": "02:42 PM"}
{"date": "02/01/2016", "responses": "208", "description": "M-bit modifier", "comments": "RAMA", "time": "02:43 PM"}
{"date": "02/01/2016", "responses": "221", "description": "T-bit BEQ modifier", "comments": "RAMA", "time": "02:45 PM"}
{"date": "02/03/2016", "responses": "205", "description": "Async discontinuity", "comments": "None", "time": "02:14 PM"}
{"date": "02/03/2016", "responses": "208", "description": "Exceptions internal", "comments": "None", "time": "02:18 PM"}
{"date": "02/03/2016", "responses": "213", "description": "OS call", "comments": "None", "time": "02:20 PM"}
{"date": "02/08/2016", "responses": "166", "description": "Test Q", "comments": "RAMA", "time": "02:06 PM"}
{"date": "02/08/2016", "responses": "172", "description": "Test Q2", "comments": "RAMA", "time": "02:07 PM"}
{"date": "02/08/2016", "responses": "202", "description": "Exec time", "comments": "RAMA", "time": "02:14 PM"}
{"date": "02/08/2016", "responses": "207", "description": "Static frequency", "comments": "RAMA", "time": "02:21 PM"}
{"date": "02/08/2016", "responses": "193", "description": "Dynamic frequency", "comments": "RAMA", "time": "02:22 PM"}
{"date": "02/08/2016", "responses": "210", "description": "Application of static frequency", "comments": "RAMA", "time": "02:25 PM"}
{"date": "02/08/2016", "responses": "206", "description": "Application of dynamic frequency", "comments": "RAMA", "time": "02:27 PM"}
{"date": "02/08/2016", "responses": "209", "description": "TSRB to CoC raw", "comments": "RAMA", "time": "02:41 PM"}
{"date": "02/08/2016", "responses": "209", "description": "Execution time comparison", "comments": "RAMA", "time": "02:44 PM"}
{"date": "02/10/2016", "responses": "164", "description": "Test clicker", "comments": "RAMA", "time": "02:05 PM"}
{"date": "02/10/2016", "responses": "172", "description": "When's the test", "comments": "RAMA", "time": "02:06 PM"}
{"date": "02/10/2016", "responses": "179", "description": "Addressing mode", "comments": "RAMA", "time": "02:08 PM"}
{"date": "02/10/2016", "responses": "190", "description": "Saving and restoring registers", "comments": "RAMA", "time": "02:09 PM"}
{"date": "02/10/2016", "responses": "190", "description": "Local variables", "comments": "RAMA", "time": "02:10 PM"}
{"date": "02/10/2016", "responses": "197", "description": "Frame pointer", "comments": "RAMA", "time": "02:10 PM"}
{"date": "02/10/2016", "responses": "200", "description": "Instruction set", "comments": "RAMA", "time": "02:13 PM"}
{"date": "02/10/2016", "responses": "194", "description": "Instruction set design", "comments": "RAMA", "time": "02:14 PM"}
{"date": "02/10/2016", "responses": "201", "description": "Endianness of an architecture", "comments": "RAMA", "time": "02:18 PM"}
{"date": "02/10/2016", "responses": "196", "description": "Number of clock cycles", "comments": "RAMA", "time": "02:22 PM"}
{"date": "02/10/2016", "responses": "205", "description": "Rows in FSM", "comments": "RAMA", "time": "02:25 PM"}
{"date": "02/10/2016", "responses": "202", "description": "Duration of a micro state", "comments": "RAMA", "time": "02:27 PM"}
{"date": "02/10/2016", "responses": "203", "description": "A trap is", "comments": "RAMA", "time": "02:27 PM"}
{"date": "02/10/2016", "responses": "204", "description": "Implicit interrupts", "comments": "RAMA", "time": "02:29 PM"}
{"date": "02/10/2016", "responses": "203", "description": "Handler saves/restores", "comments": "RAMA", "time": "02:35 PM"}
{"date": "02/10/2016", "responses": "199", "description": "Handler saves processor registers", "comments": "RAMA", "time": "02:37 PM"}
{"date": "02/10/2016", "responses": "201", "description": "RTI processor next mode", "comments": "RAMA", "time": "02:38 PM"}
{"date": "02/12/2016", "responses": "130", "description": "Clicker test", "comments": "RAMA", "time": "02:06 PM"}
{"date": "02/12/2016", "responses": "154", "description": "Wednesday's review", "comments": "RAMA", "time": "02:06 PM"}
{"date": "02/12/2016", "responses": "194", "description": "Bill 5 stages of pipeline", "comments": "RAMA", "time": "02:18 PM"}
{"date": "02/12/2016", "responses": "195", "description": "Buffers to sandwiches", "comments": "RAMA", "time": "02:40 PM"}
{"date": "02/12/2016", "responses": "189", "description": "Macro state of pipeline", "comments": "RAMA", "time": "02:48 PM"}
{"date": "02/15/2016", "responses": "192", "description": "Washing dishes", "comments": "None", "time": "02:11 PM"}
{"date": "02/15/2016", "responses": "205", "description": "Fetch after Pipelining", "comments": "None", "time": "02:23 PM"}
{"date": "02/15/2016", "responses": "203", "description": "Retry FETCH pipeline", "comments": "None", "time": "02:26 PM"}
{"date": "02/15/2016", "responses": "206", "description": "Clock cycles of piplined EXEC", "comments": "Most popular answer was wrong", "time": "02:30 PM"}
{"date": "02/15/2016", "responses": "204", "description": "General case of ID/RR buffer size", "comments": "None", "time": "02:42 PM"}
{"date": "02/15/2016", "responses": "200", "description": "Stuff in register after ID/RR stage", "comments": "None", "time": "02:48 PM"}
{"date": "02/17/2016", "responses": "202", "description": "Hazard of Ry + Rz + Imm", "comments": "None", "time": "02:43 PM"}
{"date": "02/17/2016", "responses": "199", "description": "Hazard of branching instruction", "comments": "None", "time": "02:53 PM"}
{"date": "02/19/2016", "responses": "173", "description": "Busy bit on two instructions", "comments": "None", "time": "02:08 PM"}
{"date": "02/19/2016", "responses": "189", "description": "The busy bit will be cleared when...", "comments": "None", "time": "02:27 PM"}
{"date": "02/19/2016", "responses": "187", "description": "Forwarding NAND", "comments": "None", "time": "02:47 PM"}
{"date": "02/22/2016", "responses": "141", "description": "Test clickers", "comments": "RAMA", "time": "02:07 PM"}
{"date": "02/22/2016", "responses": "165", "description": "Macro state of pipelined processor", "comments": "RAMA", "time": "02:08 PM"}
{"date": "02/22/2016", "responses": "175", "description": "Teach pipelining or scheduling", "comments": "RAMA", "time": "02:09 PM"}
{"date": "02/22/2016", "responses": "184", "description": "What causes a structural hazard", "comments": "RAMA", "time": "02:11 PM"}
{"date": "02/22/2016", "responses": "195", "description": "Reduced bubbles", "comments": "RAMA", "time": "02:15 PM"}
{"date": "02/22/2016", "responses": "192", "description": "Bubbles for conservative branching", "comments": "RAMA", "time": "02:47 PM"}
{"date": "02/22/2016", "responses": "189", "description": "Bubbles for conservative branching (again)", "comments": "RAMA", "time": "02:50 PM"}
{"date": "02/22/2016", "responses": "183", "description": "Number of bubbles with branch prediction", "comments": "RAMA", "time": "02:53 PM"}
{"date": "02/24/2016", "responses": "167", "description": "Test clickers", "comments": "RAMA", "time": "02:05 PM"}
{"date": "02/24/2016", "responses": "184", "description": "What is a process?", "comments": "RAMA", "time": "02:11 PM"}
{"date": "02/24/2016", "responses": "191", "description": "What is a scheduler?", "comments": "RAMA", "time": "02:23 PM"}
{"date": "02/24/2016", "responses": "190", "description": "Number of programs in a modern OS", "comments": "RAMA", "time": "02:34 PM"}
{"date": "02/24/2016", "responses": "193", "description": "What are threads?", "comments": "RAMA", "time": "02:35 PM"}
{"date": "02/24/2016", "responses": "189", "description": "What's not in the PCB?", "comments": "RAMA", "time": "02:44 PM"}
{"date": "02/24/2016", "responses": "183", "description": "What's preemptive scheduling?", "comments": "RAMA", "time": "02:54 PM"}
{"date": "02/26/2016", "responses": "171", "description": "Disadvantage of FCFS schedulers", "comments": "None", "time": "02:26 PM"}
{"date": "02/26/2016", "responses": "152", "description": "When does CPU become idle?", "comments": "None", "time": "02:48 PM"}
{"date": "02/29/2016", "responses": "181", "description": "Which is called once per process?", "comments": "None", "time": "02:08 PM"}
{"date": "02/29/2016", "responses": "184", "description": "Which is called once per process (again)?", "comments": "None", "time": "02:13 PM"}
{"date": "02/29/2016", "responses": "189", "description": "Which schedulers suffer from starvation?", "comments": "None", "time": "02:36 PM"}
{"date": "03/02/2016", "responses": "196", "description": "What types of fragmentation could paging experience?", "comments": "None", "time": "02:43 PM"}
{"date": "03/02/2016", "responses": "160", "description": "Page size of 12-bit offsets.", "comments": "None", "time": "02:55 PM"}
{"date": "03/04/2016", "responses": "108", "description": "Test question", "comments": "RAMA", "time": "02:07 PM"}
{"date": "03/04/2016", "responses": "181", "description": "Entries in page table by address size", "comments": "RAMA", "time": "02:23 PM"}
{"date": "03/04/2016", "responses": "182", "description": "Frames in physical memory", "comments": "None", "time": "02:24 PM"}
{"date": "03/04/2016", "responses": "171", "description": "Page tables in memory?", "comments": "RAMA", "time": "02:24 PM"}
